python_schematized_config-0.1.0.dist-info/licenses/LICENSE
schematized_config/__init__.py
schematized_config/_modidx.py
schematized_config/cli.py
schematized_config/core.py
python_schematized_config-0.1.0.dist-info/METADATA
python_schematized_config-0.1.0.dist-info/WHEEL
python_schematized_config-0.1.0.dist-info/entry_points.txt
python_schematized_config-0.1.0.dist-info/top_level.txt
python_schematized_config-0.1.0.dist-info/RECORD
