Metadata-Version: 2.4
Name: python-schematized-config
Version: 0.1.0
Summary: validate configs using json schema
Home-page: https://github.com/tutankalex/python-schematized-config
Author: tutankalex
Author-email: 109660532+tutankalex@users.noreply.github.com
License: Apache Software License 2.0
Keywords: nbdev jupyter notebook python
Classifier: Development Status :: 4 - Beta
Classifier: Intended Audience :: Developers
Classifier: Natural Language :: English
Classifier: Programming Language :: Python :: 3.7
Classifier: Programming Language :: Python :: 3.8
Classifier: Programming Language :: Python :: 3.9
Classifier: Programming Language :: Python :: 3.10
Classifier: License :: OSI Approved :: Apache Software License
Requires-Python: >=3.7
License-File: LICENSE
Requires-Dist: jsonschema>=4.17.3
Requires-Dist: python-dotenv>=1.0.0
Requires-Dist: fsspec>=2023.12.0
Requires-Dist: nbdev>=2.4.2
Requires-Dist: pydantic>=2
Provides-Extra: dev
Dynamic: author
Dynamic: author-email
Dynamic: classifier
Dynamic: description
Dynamic: description-content-type
Dynamic: home-page
Dynamic: keywords
Dynamic: license
Dynamic: license-file
Dynamic: provides-extra
Dynamic: requires-dist
Dynamic: requires-python
Dynamic: summary
